vsrl/__init__.py
vsrl/caos/__init__.py
vsrl/caos/caos.py
vsrl/parser/__init__.py
vsrl/parser/parser.py
vsrl/rl/__init__.py
vsrl/rl/agents/__init__.py
vsrl/rl/agents/agent.py
vsrl/rl/agents/rlpyt_agent.py
vsrl/rl/envs/__init__.py
vsrl/rl/envs/_utils.py
vsrl/rl/envs/acc.py
vsrl/rl/envs/env.py
vsrl/rl/envs/pm_goal_finding.py
vsrl/rl/envs/pointmesses.py
vsrl/rl/envs/render_helpers.py
vsrl/rl/envs/safety_wrappers.py
vsrl/rl/rlpyt/__init__.py
vsrl/rl/rlpyt/agents.py
vsrl/rl/rlpyt/algos.py
vsrl/rl/rlpyt/collectors.py
vsrl/rl/rlpyt/env.py
vsrl/rl/rlpyt/loggers.py
vsrl/rl/rlpyt/models.py
vsrl/rl/rlpyt/runners.py
vsrl/spaces/__init__.py
vsrl/spaces/continuous.py
vsrl/spaces/fin_space.py
vsrl/spaces/space.py
vsrl/spaces/space_helpers.py
vsrl/symmap/__init__.py
vsrl/symmap/data.py
vsrl/symmap/symbolic_mapper.py
vsrl/symmap/utils.py
vsrl/symmap/detectors/__init__.py
vsrl/symmap/detectors/center_track.py
vsrl/symmap/detectors/qatm.py
vsrl/symmap/detectors/template_matching.py
vsrl/symmap/detectors/utils.py
vsrl/training/__init__.py
vsrl/training/train_detector.py
vsrl/training/train_rl.py
vsrl/utils/__init__.py
vsrl/utils/assets.py
vsrl/utils/logger.py
vsrl/utils/utils.py
vsrl/utils/visualization.py
vsrl/verifier/__init__.py
vsrl/verifier/expr.py
vsrl/verifier/expr_helpers.py
vsrl/verifier/keymaerax.py
vsrl/verifier/keymaerax_pretty_printer.py
vsrl/verifier/monitor.py
vsrl/verifier/ode_helpers.py
vsrl/verifier/traversal.py
vsrl-0.0.1.dist-info/licenses/LICENSE.txt
vsrl-0.0.1.dist-info/METADATA
vsrl-0.0.1.dist-info/WHEEL
vsrl-0.0.1.dist-info/top_level.txt
vsrl-0.0.1.dist-info/RECORD
